README.md
setup.cfg
setup.py
pp_l3_distributions/Binomialdistribution.py
pp_l3_distributions/Gaussiandistribution.py
pp_l3_distributions/Generaldistribution.py
pp_l3_distributions/__init__.py
pp_l3_distributions.egg-info/PKG-INFO
pp_l3_distributions.egg-info/SOURCES.txt
pp_l3_distributions.egg-info/dependency_links.txt
pp_l3_distributions.egg-info/not-zip-safe
pp_l3_distributions.egg-info/top_level.txt